biomatx/__init__.py
biomatx-0.0.8.dist-info/WHEEL
biomatx-0.0.8.dist-info/METADATA
biomatx-0.0.8.dist-info/licenses/LICENSE
biomatx-0.0.8.dist-info/RECORD
