Metadata-Version: 2.1
Name: biomatx
Version: 0.0.8
Summary: Python API for managing the Biomatx home automation system
License: MIT
Author-email: Damien Merenne <dam@cosinux.org>
Requires-Python: >=3.9
Classifier: Development Status :: 3 - Alpha
Requires-Dist: pyserial-asyncio~=0.6
Project-URL: Homepage, https://github.com/canatella/pybiomatx
Project-URL: Repository, https://github.com/canatella/pybiomatx
